markdown_crawler/__init__.py
markdown_crawler/cli.py
markdown_crawler-0.0.8.dist-info/LICENSE.txt
markdown_crawler-0.0.8.dist-info/METADATA
markdown_crawler-0.0.8.dist-info/WHEEL
markdown_crawler-0.0.8.dist-info/entry_points.txt
markdown_crawler-0.0.8.dist-info/top_level.txt
markdown_crawler-0.0.8.dist-info/RECORD
