Metadata-Version: 2.1
Name: markdown-crawler
Version: 0.0.8
Summary: A multithreaded 🕸️ web crawler that recursively crawls a website and creates a 🔽 markdown file for each page
Author-email: Paul Pierre <hi@paulpierre.com>
Project-URL: Homepage, https://github.com/paulpierre/markdown-crawler
Project-URL: Bug Tracker, https://github.com/paulpierre/markdown-crawler/issues
Project-URL: Twitter, https://twitter.com/paulpierre
Classifier: Programming Language :: Python :: 3
Classifier: License :: OSI Approved :: MIT License
Classifier: Operating System :: OS Independent
Requires-Python: >=3.4
License-File: LICENSE.txt
